yadbox/__init__.py
yadbox/export.py
yadbox/kinematics.py
yadbox/runcards/__init__.py
yadbox/runcards/theory.py
yadism/__init__.py
yadism/coefficient_functions/__init__.py
yadism/coefficient_functions/asy/__init__.py
yadism/coefficient_functions/asy/f2_cc.py
yadism/coefficient_functions/asy/f2_nc.py
yadism/coefficient_functions/asy/f3_cc.py
yadism/coefficient_functions/asy/f3_nc.py
yadism/coefficient_functions/asy/fl_cc.py
yadism/coefficient_functions/asy/fl_nc.py
yadism/coefficient_functions/asy/g1_nc.py
yadism/coefficient_functions/asy/g1_nc_raw.py
yadism/coefficient_functions/asy/g4_nc.py
yadism/coefficient_functions/asy/gl_nc.py
yadism/coefficient_functions/asy/kernels.py
yadism/coefficient_functions/asy/partonic_channel.py
yadism/coefficient_functions/asy/raw_nc.py
yadism/coefficient_functions/coupling_constants.py
yadism/coefficient_functions/heavy/__init__.py
yadism/coefficient_functions/heavy/f2_cc.py
yadism/coefficient_functions/heavy/f2_nc.py
yadism/coefficient_functions/heavy/f3_cc.py
yadism/coefficient_functions/heavy/f3_nc.py
yadism/coefficient_functions/heavy/fl_cc.py
yadism/coefficient_functions/heavy/fl_nc.py
yadism/coefficient_functions/heavy/g1_nc.py
yadism/coefficient_functions/heavy/g4_nc.py
yadism/coefficient_functions/heavy/gl_nc.py
yadism/coefficient_functions/heavy/kernels.py
yadism/coefficient_functions/heavy/n3lo/__init__.py
yadism/coefficient_functions/heavy/n3lo/grids/C2g_nf3_var-1.npy
yadism/coefficient_functions/heavy/n3lo/grids/C2g_nf3_var0.npy
yadism/coefficient_functions/heavy/n3lo/grids/C2g_nf3_var1.npy
yadism/coefficient_functions/heavy/n3lo/grids/C2g_nf4_var-1.npy
yadism/coefficient_functions/heavy/n3lo/grids/C2g_nf4_var0.npy
yadism/coefficient_functions/heavy/n3lo/grids/C2g_nf4_var1.npy
yadism/coefficient_functions/heavy/n3lo/grids/C2g_nf5_var-1.npy
yadism/coefficient_functions/heavy/n3lo/grids/C2g_nf5_var0.npy
yadism/coefficient_functions/heavy/n3lo/grids/C2g_nf5_var1.npy
yadism-0.13.9.dist-info/METADATA
yadism-0.13.9.dist-info/WHEEL
yadism-0.13.9.dist-info/entry_points.txt
yadism-0.13.9.dist-info/licenses/LICENSE
yadism-0.13.9.dist-info/RECORD
