Metadata-Version: 2.4
Name: yadism
Version: 0.13.9
Summary: Yet Another Deep-Inelastic Scattering Module
License: GPL-3.0-only
License-File: LICENSE
Author: Alessandro Candido
Author-email: alessandro.candido@mi.infn.it
Requires-Python: >=3.9,<3.14
Classifier: License :: OSI Approved :: GNU General Public License v3 (GPLv3)
Classifier: Operating System :: Unix
Classifier: Programming Language :: Python
Classifier: Programming Language :: Python :: 3
Classifier: Programming Language :: Python :: 3.9
Classifier: Programming Language :: Python :: 3.10
Classifier: Programming Language :: Python :: 3.11
Classifier: Programming Language :: Python :: 3.12
Classifier: Programming Language :: Python :: 3.13
Classifier: Topic :: Scientific/Engineering
Classifier: Topic :: Scientific/Engineering :: Physics
Provides-Extra: box
Provides-Extra: mark
Requires-Dist: LeProHQ (>=0.2.5,<0.3.0)
Requires-Dist: adani (>=1.0.2,<2.0.0)
Requires-Dist: banana-hep (>=0.6.13,<0.7.0) ; extra == "mark"
Requires-Dist: eko (>=0.15.2)
Requires-Dist: numba (>=0.59.0,<=0.62.0)
Requires-Dist: numpy (>=2)
Requires-Dist: pandas (>=2.1.4,<3.0.0)
Requires-Dist: pineappl (>=1.1.0,<2.0.0) ; extra == "box"
Requires-Dist: rich (>=12.4.4,<13.0.0)
Requires-Dist: scipy (>=1.10.0,<2.0.0)
Requires-Dist: sqlalchemy (>=1.4.21,<2.0.0) ; extra == "mark"
Project-URL: Coverage, https://codecov.io/gh/N3PDF/yadism
Project-URL: Changelog, https://github.com/N3PDF/yadism/releases
Project-URL: Documentation, https://yadism.readthedocs.io/
Project-URL: Homepage, https://n3pdf.github.io/yadism/
Project-URL: Issue Tracker, https://github.com/N3PDF/yadism/issues
Project-URL: Repository, https://github.com/N3PDF/yadism/
